{
  "id": "0926e450-e8f1-487b-ba4e-ec98498e622e",
  "title": "kuis",
  "author": "",
  "description": "own course",
  "license": "by-sa",
  "metadata": {
    "author": {},
    "site": {
      "name": "kuis",
      "logo": "assets/banner.jpg",
      "settings": {
        "lang": "en-US",
        "publishPagesOn": true,
        "canonical": true
      },
      "created": 1762212603,
      "updated": 1763610617,
      "git": {
        "vendor": "github",
        "branch": "gh-pages"
      }
    },
    "theme": {
      "element": "custom-kuis-theme",
      "path": "./custom/build/custom.es6.js",
      "name": "CustomKuisTheme"
    },
    "node": {
      "fields": {}
    },
    "build": {
      "version": "11.0.5",
      "structure": "course",
      "type": "own"
    }
  },
  "items": [
    {
      "id": "item-b3767224-058a-4031-a276-bae9e4a79b7a",
      "indent": 0,
      "location": "pages/item-b3767224-058a-4031-a276-bae9e4a79b7a/index.html",
      "slug": "welcome",
      "order": 0,
      "parent": null,
      "title": "Welcome to kuis",
      "description": "",
      "metadata": {
        "created": 1762212602,
        "updated": 1762212602
      }
    },
    {
      "id": "item-2dabd214-5a54-4405-89d9-455237ac8b8c",
      "indent": 0,
      "location": "pages/item-2dabd214-5a54-4405-89d9-455237ac8b8c/index.html",
      "slug": "page",
      "order": 1,
      "parent": null,
      "title": "Page",
      "description": "\n\nDeep thoughts..\nI at times, enjoy coffee. Those times, are all times.\nItemItem\nHeading\n",
      "metadata": {
        "created": 1762212838,
        "updated": 1762213104,
        "images": {},
        "videos": {},
        "published": true,
        "hideInMenu": false,
        "locked": false,
        "readtime": 1,
        "files": [
          {
            "path": "C:\\Users\\Administrator\\Downloads\\git\\andyprodistik\\kuis\\files\\kucing.jpg",
            "fullUrl": "/C:\\Users\\Administrator\\Downloads\\git\\andyprodistik\\kuis/files/kucing.jpg",
            "url": "files/kucing.jpg",
            "type": "image/jpeg",
            "name": "kucing.jpg",
            "size": 17200
          }
        ]
      }
    },
    {
      "id": "item-kuis-simple",
      "indent": 0,
      "location": "pages/item-kuis/index.html",
      "slug": "kuis",
      "order": 6,
      "parent": null,
      "title": "Kuis (atribut)",
      "description": "",
      "metadata": {
        "created": 1762218999,
        "updated": 1762218999,
        "published": true,
        "hideInMenu": false,
        "locked": false,
        "readtime": 1
      }
    },
    {
      "id": "item-9b15cf15-bf48-4ef0-837a-d45637b0224e",
      "indent": 0,
      "location": "pages/item-9b15cf15-bf48-4ef0-837a-d45637b0224e/index.html",
      "slug": "page-3",
      "order": 5,
      "parent": null,
      "title": "Page",
      "description": "",
      "metadata": {
        "created": 1762221614,
        "updated": 1762221614,
        "images": [],
        "videos": []
      }
    },
    {
      "id": "item-43e971d7-5260-4e77-b1bd-6067bb22d2c2",
      "indent": 0,
      "location": "pages/item-43e971d7-5260-4e77-b1bd-6067bb22d2c2/index.html",
      "slug": "page-1",
      "order": 2,
      "parent": null,
      "title": "Page",
      "description": "\n",
      "metadata": {
        "created": 1763610571,
        "updated": 1763610617,
        "images": {},
        "videos": {},
        "theme": {
          "element": "haxcms-blank-theme",
          "path": "@haxtheweb/haxcms-elements/lib/core/themes/haxcms-blank-theme.js",
          "name": "Blank theme",
          "thumbnail": "build/es6/node_modules/@haxtheweb/app-hax/lib/assets/images/GreyStyle.svg",
          "key": "haxcms-blank-theme"
        },
        "published": true,
        "hideInMenu": false,
        "locked": false,
        "readtime": 1
      }
    }
  ]
}